MANIFEST.in
README.rst
flozer_unicorn_example.json
flozer_xns_example.json
setup.py
flozer/__init__.py
flozer/flozer.py
flozer/lib.py
flozer/utils.py
flozer.egg-info/PKG-INFO
flozer.egg-info/SOURCES.txt
flozer.egg-info/dependency_links.txt
flozer.egg-info/entry_points.txt
flozer.egg-info/top_level.txt