Metadata-Version: 1.1
Name: flozer
Version: 1.7
Summary: openflow parser
Home-page: https://github.com/tr3buchet/flozer
Author: Trey Morris
Author-email: trey@treymorris.com
License: Apache Software License
Keywords: github,ovs,openflow,flow,parse,parser,parsing
Platform: UNKNOWN
Classifier: Development Status :: 5 - Production/Stable
Classifier: License :: OSI Approved :: Apache Software License
